quickmatch/__init__.py
quickmatch/__main__.py
quickmatch/ArcFace/__init__.py
quickmatch/ArcFace/cfg.py
quickmatch/ArcFace/dataset.py
quickmatch/ArcFace/eval_ijbc.py
quickmatch/ArcFace/flops.py
quickmatch/ArcFace/inference.py
quickmatch/ArcFace/losses.py
quickmatch/ArcFace/lr_scheduler.py
quickmatch/ArcFace/onnx_helper.py
quickmatch/ArcFace/onnx_ijbc.py
quickmatch/ArcFace/partial_fc.py
quickmatch/ArcFace/partial_fc_v2.py
quickmatch/ArcFace/torch2onnx.py
quickmatch/ArcFace/train.py
quickmatch/ArcFace/train_v2.py
quickmatch/ArcFace/backbones/__init__.py
quickmatch/ArcFace/backbones/iresnet.py
quickmatch/ArcFace/backbones/iresnet2060.py
quickmatch/ArcFace/backbones/mobilefacenet.py
quickmatch/ArcFace/backbones/vit.py
quickmatch/ArcFace/configs/3millions.py
quickmatch/ArcFace/configs/__init__.py
quickmatch/ArcFace/configs/base.py
quickmatch/ArcFace/configs/glint360k_mbf.py
quickmatch/ArcFace/configs/glint360k_r100.py
quickmatch/ArcFace/configs/glint360k_r50.py
quickmatch/ArcFace/configs/ms1mv2_mbf.py
quickmatch/ArcFace/configs/ms1mv2_r100.py
quickmatch/ArcFace/configs/ms1mv2_r50.py
quickmatch/ArcFace/configs/ms1mv3_mbf.py
quickmatch/ArcFace/configs/ms1mv3_r100.py
quickmatch/ArcFace/configs/ms1mv3_r50.py
quickmatch/ArcFace/configs/wf12m_conflict_r50.py
quickmatch/ArcFace/configs/wf12m_conflict_r50_pfc03_filter04.py
quickmatch/ArcFace/configs/wf12m_flip_pfc01_filter04_r50.py
quickmatch/ArcFace/configs/wf12m_flip_r50.py
quickmatch/ArcFace/configs/wf12m_mbf.py
quickmatch/ArcFace/configs/wf12m_pfc02_r100.py
quickmatch/ArcFace/configs/wf12m_r100.py
quickmatch/ArcFace/configs/wf12m_r50.py
quickmatch/ArcFace/configs/wf42m_pfc0008_32gpu_r100.py
quickmatch/ArcFace/configs/wf42m_pfc02_16gpus_mbf_bs8k.py
quickmatch/ArcFace/configs/wf42m_pfc02_16gpus_r100.py
quickmatch/ArcFace/configs/wf42m_pfc02_16gpus_r50_bs8k.py
quickmatch/ArcFace/configs/wf42m_pfc02_32gpus_r50_bs4k.py
quickmatch/ArcFace/configs/wf42m_pfc02_8gpus_r50_bs4k.py
quickmatch/ArcFace/configs/wf42m_pfc02_r100.py
quickmatch-0.1.0.dist-info/LICENSE
quickmatch-0.1.0.dist-info/METADATA
quickmatch-0.1.0.dist-info/WHEEL
quickmatch-0.1.0.dist-info/entry_points.txt
quickmatch-0.1.0.dist-info/top_level.txt
quickmatch-0.1.0.dist-info/RECORD
