Metadata-Version: 2.1
Name: quickmatch
Version: 0.1.0
Summary: A command-line tool for obtaining face-matcher embeddings across 4 SOTA face-matchers.
Home-page: https://github.com/jaisidhsingh/quickmatch
Author: Jaisidh Singh
Author-email: jaisidhsingh@gmail.com
License: UNKNOWN
Platform: UNKNOWN
Classifier: Programming Language :: Python :: 3
Classifier: License :: OSI Approved :: MIT License
Classifier: Operating System :: OS Independent
Requires-Python: >=3.6
Requires-Dist: numpy ==1.26.4
Requires-Dist: torch ==2.2.2
Requires-Dist: easydict ==1.13
Requires-Dist: facenet-pytorch ==2.6.0
Requires-Dist: tqdm ==4.66.4
Requires-Dist: onedrivedownloader ==1.1.3
